{"cameraMode":{"drawMode":0,"name":"Shaded","section":"Shading Mode"},"sceneLighting":false,"audioPlay":false,"sceneViewState":{"m_AlwaysRefresh":false,"showFog":true,"showSkybox":false,"showFlares":true,"showImageEffects":true,"showParticleSystems":true,"showVisualEffectGraphs":true,"m_FxEnabled":true},"in2DMode":false,"pivot":{"x":-14.776533126831055,"y":8.95656681060791,"z":-11.445274353027344},"rotation":{"x":-0.0210872869938612,"y":-0.9789562821388245,"z":0.14226505160331727,"w":-0.14521516859531403},"size":0.6490140557289124,"orthographic":false}